element_api/__init__.py
element_api/__main__.py
element_api/core.py
element_api-0.1.0.dist-info/LICENSE
element_api-0.1.0.dist-info/WHEEL
element_api-0.1.0.dist-info/METADATA
element_api-0.1.0.dist-info/RECORD
