Metadata-Version: 2.1
Name: element-api
Version: 0.1.0
Summary: Convert any python module to FastAPI compatible server. YoCo!
License: MIT
Author: yashbonde
Author-email: bonde.yash97@gmail.com
Requires-Python: >=3.9,<4.0
Classifier: License :: OSI Approved :: MIT License
Classifier: Programming Language :: Python :: 3
Classifier: Programming Language :: Python :: 3.9
Requires-Dist: fire (>=0.4.0,<0.5.0)
